setup.cfg
setup.py
selenium_respectful/__init__.py
selenium_respectful/exceptions.py
selenium_respectful/respectful_webdriver.py
selenium_respectful.egg-info/PKG-INFO
selenium_respectful.egg-info/SOURCES.txt
selenium_respectful.egg-info/dependency_links.txt
selenium_respectful.egg-info/not-zip-safe
selenium_respectful.egg-info/requires.txt
selenium_respectful.egg-info/top_level.txt