Metadata-Version: 1.1
Name: selenium-respectful
Version: 0.1.0
Summary: Minimalist Selenium webdriver wrapper to work within rate limits of any amount of services simultaneously. Parallel processing friendly.
Home-page: https://github.com/nbrochu/selenium-respectful
Author: Nicholas Brochu
Author-email: nicholas@serpent.ai
License: Apache License v2
Platform: UNKNOWN
Classifier: Development Status :: 5 - Production/Stable
Classifier: Intended Audience :: Developers
Classifier: Natural Language :: English
Classifier: License :: OSI Approved :: Apache Software License
Classifier: Programming Language :: Python
Classifier: Programming Language :: Python :: 2.7
Classifier: Programming Language :: Python :: 3
Classifier: Programming Language :: Python :: 3.2
Classifier: Programming Language :: Python :: 3.3
Classifier: Programming Language :: Python :: 3.4
Classifier: Programming Language :: Python :: 3.5
Classifier: Programming Language :: Python :: 3.6
